LICENSE
MANIFEST.in
README.md
setup.py
pusherclientb/__init__.py
pusherclientb/channel.py
pusherclientb/connection.py
pusherclientb.egg-info/PKG-INFO
pusherclientb.egg-info/SOURCES.txt
pusherclientb.egg-info/dependency_links.txt
pusherclientb.egg-info/requires.txt
pusherclientb.egg-info/top_level.txt