Metadata-Version: 1.1
Name: pusherclientb
Version: 0.3.1
Summary: Pusher websocket client for python
Home-page: https://github.com/bartbroere/PythonPusherClient
Author: Bart Broere
Author-email: mail@bartbroere.eu
License: MIT
Keywords: pusher websocket client
Platform: UNKNOWN
Classifier: Development Status :: 3 - Alpha
Classifier: Environment :: Web Environment
Classifier: License :: OSI Approved :: MIT License
Classifier: Programming Language :: Python
Classifier: Programming Language :: Python :: 2
Classifier: Programming Language :: Python :: 2.7
Classifier: Programming Language :: Python :: 3
Classifier: Programming Language :: Python :: 3.2
Classifier: Programming Language :: Python :: 3.3
Classifier: Programming Language :: Python :: 3.4
Classifier: Topic :: Internet
